happyly/__init__.py
happyly/exceptions.py
happyly/_deprecations/__init__.py
happyly/_deprecations/utils.py
happyly/caching/__init__.py
happyly/caching/cacher.py
happyly/caching/mixins.py
happyly/google_pubsub/__init__.py
happyly/google_pubsub/deserializers.py
happyly/google_pubsub/publishers.py
happyly/google_pubsub/redis_cacher.py
happyly/google_pubsub/subscribers.py
happyly/google_pubsub/high_level/__init__.py
happyly/google_pubsub/high_level/base.py
happyly/google_pubsub/high_level/early_ack.py
happyly/google_pubsub/high_level/late_ack.py
happyly/google_pubsub/high_level/simple.py
happyly/google_pubsub/high_level/with_cache.py
happyly/handling/__init__.py
happyly/handling/dummy_handler.py
happyly/handling/handler.py
happyly/listening/__init__.py
happyly/listening/executor.py
happyly/listening/listener.py
happyly/logs/__init__.py
happyly/logs/base.py
happyly/logs/request_id.py
happyly/pubsub/__init__.py
happyly/pubsub/publisher.py
happyly/pubsub/subscriber.py
happyly/schemas/__init__.py
happyly/schemas/schema.py
happyly/serialization/__init__.py
happyly/serialization/deserializer.py
happyly/serialization/dummy.py
happyly/serialization/flask.py
happyly/serialization/json.py
happyly/serialization/serializer.py
happyly/utils/generator_check.py
happyly-0.9.0.dist-info/LICENSE
happyly-0.9.0.dist-info/WHEEL
happyly-0.9.0.dist-info/METADATA
happyly-0.9.0.dist-info/RECORD
