Metadata-Version: 2.1
Name: happyly
Version: 0.9.0
Summary: Conveniently separate your business logic from messaging stuff.
Home-page: https://github.com/equeumco/happyly
License: MIT for code, CC BY-NC-SA 4.0 for images and docs
Author: Alexander Tsukanov
Author-email: aliaksandr.tsukanau@itechart-group.com
Requires-Python: >=3.6
Classifier: Development Status :: 4 - Beta
Classifier: Intended Audience :: Developers
Classifier: Topic :: Software Development :: Libraries :: Python Modules
Classifier: Topic :: Software Development :: Object Brokering
Classifier: License :: OSI Approved :: MIT License
Classifier: Programming Language :: Python :: 3.6
Classifier: Programming Language :: Python :: 3.7
Requires-Dist: attrs>=19.1
Requires-Dist: marshmallow>=2.15,<3
Requires-Dist: bump2version>=0.5.10; extra == "dev"
Requires-Dist: pre-commit>=1.14.4; extra == "dev"
Requires-Dist: sphinx>=2.0.0; extra == "doc"
Requires-Dist: sphinx-rtd-theme>=0.4.3; extra == "doc"
Requires-Dist: sphinx-autodoc-typehints>=1.6.0; extra == "doc"
Requires-Dist: flask>=1.0; extra == "flask"
Requires-Dist: google-cloud-pubsub>=0.37.2; extra == "google-cloud-pubsub"
Requires-Dist: redis>=3.0; extra == "redis"
Requires-Dist: pytest>=4.3.0; extra == "test"
Requires-Dist: tox>=3.7.0; extra == "test"
Project-URL: Documentation, https://happyly.readthedocs.io/en/latest/
Provides-Extra: dev
Provides-Extra: doc
Provides-Extra: flask
Provides-Extra: google-cloud-pubsub
Provides-Extra: redis
Provides-Extra: test
